grlc/__init__.py
grlc/__version__.py
grlc/fileLoaders.py
grlc/glogging.py
grlc/gquery.py
grlc/pagination.py
grlc/prov.py
grlc/queryTypes.py
grlc/server.py
grlc/sparql.py
grlc/static.py
grlc/swagger.py
grlc/utils.py
grlc/static/favicon.ico
grlc/static/grlc_logo_01.png
grlc/static/grlc_logo_02.png
grlc/static/toolinfo.json
grlc/static/css/grlc.css
grlc/static/js/grlc-api.js
grlc/static/js/grlc-layout.js
grlc/templates/api-docs.html
grlc/templates/index.html
grlc-1.3.10.data/data/citation/grlc/CITATION.cff
grlc-1.3.10.data/scripts/grlc-server
grlc-1.3.10.dist-info/LICENSE.txt
grlc-1.3.10.dist-info/METADATA
grlc-1.3.10.dist-info/WHEEL
grlc-1.3.10.dist-info/top_level.txt
grlc-1.3.10.dist-info/RECORD
