Metadata-Version: 2.1
Name: grlc
Version: 1.3.10
Summary: grlc, the git repository linked data API constructor
Home-page: https://github.com/CLARIAH/grlc
Author: Albert Meroño
Author-email: albert.merono@vu.nl
License: Copyright 2017 Albert Meroño
License-File: LICENSE.txt
Requires-Dist: docopt-ng==0.9.0
Requires-Dist: Flask==3.1.0
Requires-Dist: Flask-Cors==5.0.1
Requires-Dist: pyaml==25.1.0
Requires-Dist: python-gitlab==5.6.0
Requires-Dist: rdflib==7.1.3
Requires-Dist: requests==2.32.3
Requires-Dist: SPARQLTransformer==2.4.0
Requires-Dist: PyGithub==2.6.1
Requires-Dist: gunicorn==23.0.0; sys_platform != "win32"
Requires-Dist: waitress>=1.4.2; sys_platform == "win32"
